discomat/__init__.py
discomat/cuds/__init__.py
discomat/cuds/cuds.py
discomat/cuds/utils.py
discomat/ontology/__inint__.py
discomat/ontology/__init__.py
discomat/ontology/namespaces.py
discomat/ontology/ontomap.py
discomat/session/__init__.py
discomat/session/engine.py
discomat/session/session.py
discomat/session/session_manager.py
discomat/visualisation/__init__.py
discomat/visualisation/cuds_vis.py
examples/DOME40workflow1.2.py
examples/DOME40workflow1.3.py
examples/DOME40workflow1.3AH.py
examples/DOME40workflow1.3_withQuery.py
examples/check_session.py
examples/cuds.py
examples/cuds_ops.py
examples/dome4workflow.py
examples/fill_graphs_query.py
examples/gvis.py
examples/iter_graphs_in_session.py
examples/remove_graph_from_session.py
examples/session1.py
examples/session2.py
examples/session3.py
examples/session_add_cuds.py
examples/session_dome.py
examples/test_pyvis_options.py
examples/test_short_uuid.py
examples/test_to_iri.py
examples/words.py
discomat-0.2.31.dist-info/LICENSE
discomat-0.2.31.dist-info/METADATA
discomat-0.2.31.dist-info/WHEEL
discomat-0.2.31.dist-info/top_level.txt
discomat-0.2.31.dist-info/RECORD
