Metadata-Version: 2.1
Name: discomat
Version: 0.2.31
Summary: The Materials Discovery Package replacing SimPhoNy 4.0, (C) Adham Hashibon
Author-email: The Materials Discovery Group at UCL <a.hashibon@ucl.ac.uk>
License: GNU GENERAL PUBLIC LICENSE
Project-URL: homepage, https://materials-discovery.org/discomat
Project-URL: repository, https://github.com/materials-discovery/discomat
Requires-Python: >=3.7
License-File: LICENSE
